faust_prometheus_monitor/__init__.py
faust_prometheus_monitor/metrics.py
faust_prometheus_monitor/monitor.py
faust_prometheus_monitor-0.1.7.dist-info/WHEEL
faust_prometheus_monitor-0.1.7.dist-info/METADATA
faust_prometheus_monitor-0.1.7.dist-info/RECORD
