Metadata-Version: 2.1
Name: faust-prometheus-monitor
Version: 0.1.7
Summary: prometheus monitor for faust
Author: Hamzah Qudsi
Author-email: hamzah.qudsi@kensho.com
Requires-Python: >=3.6,<4.0
Classifier: Programming Language :: Python :: 3
Classifier: Programming Language :: Python :: 3.6
Classifier: Programming Language :: Python :: 3.7
Classifier: Programming Language :: Python :: 3.8
Classifier: Programming Language :: Python :: 3.9
Requires-Dist: faust-streaming (>=0.4.6,<0.5.0)
Requires-Dist: prometheus-client (>=0.9.0,<0.10.0)
